[
    {
        "id": "f123451",
        "brand": "samsung",
        "brandImage": "https://i.ibb.co/8spC3pw/samsung-Logo.jpg"
    },
    {
        "id": "f123452",
        "brand": "walton",
        "brandImage": "https://i.ibb.co/cwmPq8B/walton-Logo.jpg"
    },
    {
        "id": "f123453",
        "brand": "apple",
        "brandImage": "https://i.ibb.co/rf6G5XZ/apple-Logo.jpg"
    },
    {
        "id": "f123454",
        "brand": "sony",
        "brandImage": "https://i.ibb.co/1KhDsFb/sonyLogo.jpg"
    },
    {
        "id": "f123455",
        "brand": "xiaomi",
        "brandImage": "https://i.ibb.co/qmwXrJK/xiaomi-Logo.jpg"
    },
    {
        "id": "f123456",
        "brand": "huawei",
        "brandImage": "https://i.ibb.co/JcVC4SQ/huawei-Logo.jpg"
    }
]